object_detection/__init__.py
object_detection/create_pascal_tf_record.py
object_detection/create_pascal_tf_record_test.py
object_detection/create_pet_tf_record.py
object_detection/eval.py
object_detection/eval_util.py
object_detection/evaluator.py
object_detection/export_inference_graph.py
object_detection/exporter.py
object_detection/exporter_test.py
object_detection/train.py
object_detection/trainer.py
object_detection/trainer_test.py
object_detection/anchor_generators/__init__.py
object_detection/anchor_generators/grid_anchor_generator.py
object_detection/anchor_generators/grid_anchor_generator_test.py
object_detection/anchor_generators/multiple_grid_anchor_generator.py
object_detection/anchor_generators/multiple_grid_anchor_generator_test.py
object_detection/box_coders/__init__.py
object_detection/box_coders/faster_rcnn_box_coder.py
object_detection/box_coders/faster_rcnn_box_coder_test.py
object_detection/box_coders/keypoint_box_coder.py
object_detection/box_coders/keypoint_box_coder_test.py
object_detection/box_coders/mean_stddev_box_coder.py
object_detection/box_coders/mean_stddev_box_coder_test.py
object_detection/box_coders/square_box_coder.py
object_detection/box_coders/square_box_coder_test.py
object_detection/builders/__init__.py
object_detection/builders/anchor_generator_builder.py
object_detection/builders/anchor_generator_builder_test.py
object_detection/builders/box_coder_builder.py
object_detection/builders/box_coder_builder_test.py
object_detection/builders/box_predictor_builder.py
object_detection/builders/box_predictor_builder_test.py
object_detection/builders/hyperparams_builder.py
object_detection/builders/hyperparams_builder_test.py
object_detection/builders/image_resizer_builder.py
object_detection/builders/image_resizer_builder_test.py
object_detection/builders/input_reader_builder.py
object_detection/builders/input_reader_builder_test.py
object_detection/builders/losses_builder.py
vcv-3.0.0.1.dist-info/DESCRIPTION.rst
vcv-3.0.0.1.dist-info/METADATA
vcv-3.0.0.1.dist-info/RECORD
vcv-3.0.0.1.dist-info/WHEEL
vcv-3.0.0.1.dist-info/entry_points.txt
vcv-3.0.0.1.dist-info/metadata.json
vcv-3.0.0.1.dist-info/top_level.txt
